Workbook

Sheet Composicao
A1: Ticker | B1: Name | C1: Sector | D1: Asset Class | E1: Market Value | F1: Weight (%) | G1: Notional Value | H1: Shares | I1: Price | J1: Location | K1: Exchange | L1: Currency | M1: FX Rate | N1: Market Currency
A2: VALE3 | B2: CIA VALE DO RIO DOCE SH | C2: Materiais | D2: Renda VariÃ¡vel | E2: 6687993.7 | F2: 11.03 | G2: 6687993.7 | H2: 122603 | I2: 54.55 | J2: Brasil | K2: XBSP | L2: BRL | M2: 1 | N2: BRL
A3: PETR4 | B3: PETROLEO BRASILEIRO PREF SA | C3: Energia | D3: Renda VariÃ¡vel | E3: 4603476.6 | F3: 7.59 | G3: 4603476.6 | H3: 127203 | I3: 36.19 | J3: Brasil | K3: XBSP | L3: BRL | M3: 1 | N3: BRL
A4: ITUB4 | B4: ITAU UNIBANCO HOLDING PREF SA | C4: Produtos financeiros | D4: Renda VariÃ¡vel | E4: 4227034.4 | F4: 6.97 | G4: 4227034.4 | H4: 137554 | I4: 30.73 | J4: Brasil | K4: XBSP | L4: BRL | M4: 1 | N4: BRL
A5: PETR3 | B5: PETROLEO BRASILEIRO SA PETROBRAS | C5: Energia | D5: Renda VariÃ¡vel | E5: 3976666 | F5: 6.56 | G5: 3976666 | H5: 100905 | I5: 39.41 | J5: Brasil | K5: XBSP | L5: BRL | M5: 1 | N5: BRL
A6: WEGE3 | B6: WEG SA | C6: Bens Industriais | D6: Renda VariÃ¡vel | E6: 2245944 | F6: 3.7 | G6: 2245944 | H6: 42561 | I6: 52.77 | J6: Brasil | K6: XBSP | L6: BRL | M6: 1 | N6: BRL
A7: BBAS3 | B7: BANCO DO BRASIL SA | C7: Produtos financeiros | D7: Renda VariÃ¡vel | E7: 1973287.1 | F7: 3.25 | G7: 1973287.1 | H7: 81642 | I7: 24.17 | J7: Brasil | K7: XBSP | L7: BRL | M7: 1 | N7: BRL
A8: ELET3 | B8: CENTRAIS ELETR BRAS-ELETROBRAS | C8: ServiÃ§os pÃºblicos | D8: Renda VariÃ¡vel | E8: 1938106.2 | F8: 3.2 | G8: 1938106.2 | H8: 56786 | I8: 34.13 | J8: Brasil | K8: XBSP | L8: BRL | M8: 1 | N8: BRL
A9: SBSP3 | B9: COMPANHIA DE SANEAMENTO BASICO DE | C9: ServiÃ§os pÃºblicos | D9: Renda VariÃ¡vel | E9: 1735750.5 | F9: 2.86 | G9: 1735750.5 | H9: 19613 | I9: 88.5 | J9: Brasil | K9: XBSP | L9: BRL | M9: 1 | N9: BRL
A10: BBDC4 | B10: BANCO BRADESCO PREF SA | C10: Produtos financeiros | D10: Renda VariÃ¡vel | E10: 1703435.4 | F10: 2.81 | G10: 1703435.4 | H10: 147356 | I10: 11.56 | J10: Brasil | K10: XBSP | L10: BRL | M10: 1 | N10: BRL
A11: B3SA3 | B11: B3 BRASIL BOLSA BALCAO SA | C11: Produtos financeiros | D11: Renda VariÃ¡vel | E11: 1633872.7 | F11: 2.69 | G11: 1633872.7 | H11: 158321 | I11: 10.32 | J11: Brasil | K11: XBSP | L11: BRL | M11: 1 | N11: BRL
A12: ABEV3 | B12: AMBEV SA | C12: Bens de primeira necessidade | D12: Renda VariÃ¡vel | E12: 1480496.2 | F12: 2.44 | G12: 1480496.2 | H12: 126107 | I12: 11.74 | J12: Brasil | K12: XBSP | L12: BRL | M12: 1 | N12: BRL
A13: ITSA4 | B13: ITAUSA INVESTIMENTOS ITAU PREF SA | C13: Produtos financeiros | D13: Renda VariÃ¡vel | E13: 1464455.5 | F13: 2.42 | G13: 1464455.5 | H13: 165850 | I13: 8.83 | J13: Brasil | K13: XBSP | L13: BRL | M13: 1 | N13: BRL
... A104: KLBN4 | B104: KLABIN SA PREF | C104: Materiais | D104: Renda VariÃ¡vel | E104: 4.59 | F104: 0 | G104: 4.59 | H104: 1 | I104: 4.59 | J104: Brasil | K104: XBSP | L104: BRL | M104: 1 | N104: BRL

Sheet Selecao_Carteira
A1: Ticker | B1: Name | C1: Sector | D1: Asset Class | E1: Market Value | F1: Weight (%) | G1: Notional Value | H1: Shares | I1: Price | J1: Location | K1: Exchange | L1: Currency | M1: FX Rate | N1: Market Currency | O1: Frequencia | P1: Percentual proporcionalizando pra 100
A2: VALE3 | B2: CIA VALE DO RIO DOCE SH | C2: Mineração | D2: Renda VariÃ¡vel | E2: 6687993.7 | F2: 11.03 | G2: 6687993.7 | H2: 122603 | I2: 54.55 | J2: Brasil | K2: XBSP | L2: BRL | M2: 1 | N2: BRL | O2: =F2 -> 11.03 | P2: =F2*100/SUM($F$2:$F$21) -> 15.99942
A3: PETR4 | B3: PETROLEO BRASILEIRO PREF SA | C3: Petroleo, Gás e Biocombustíveis | D3: Renda VariÃ¡vel | E3: 4603476.6 | F3: 7.59 | G3: 4603476.6 | H3: 127203 | I3: 36.19 | J3: Brasil | K3: XBSP | L3: BRL | M3: 1 | N3: BRL | O3: =F3+O2 -> 18.62 | P3: =F3*100/SUM($F$2:$F$21) -> 11.009574
A4: ITUB4 | B4: ITAU UNIBANCO HOLDING PREF SA | C4: Intermediários Financeiros | D4: Renda VariÃ¡vel | E4: 4227034.4 | F4: 6.97 | G4: 4227034.4 | H4: 137554 | I4: 30.73 | J4: Brasil | K4: XBSP | L4: BRL | M4: 1 | N4: BRL | O4: =F4+O3 -> 25.59 | P4: =F4*100/SUM($F$2:$F$21) -> 10.110241
A5: PETR3 | B5: PETROLEO BRASILEIRO SA PETROBRAS | C5: Petroleo, Gás e Biocombustíveis | D5: Renda VariÃ¡vel | E5: 3976666 | F5: 6.56 | G5: 3976666 | H5: 100905 | I5: 39.41 | J5: Brasil | K5: XBSP | L5: BRL | M5: 1 | N5: BRL | O5: =F5+O4 -> 32.15 | P5: =F5*100/SUM($F$2:$F$21) -> 9.5155207
A6: WEGE3 | B6: WEG SA | C6: Máquinas e Equipamentos | D6: Renda VariÃ¡vel | E6: 2245944 | F6: 3.7 | G6: 2245944 | H6: 42561 | I6: 52.77 | J6: Brasil | K6: XBSP | L6: BRL | M6: 1 | N6: BRL | O6: =F6+O5 -> 35.85 | P6: =F6*100/SUM($F$2:$F$21) -> 5.3669858
A7: BBAS3 | B7: BANCO DO BRASIL SA | C7: Intermediários Financeiros | D7: Renda VariÃ¡vel | E7: 1973287.1 | F7: 3.25 | G7: 1973287.1 | H7: 81642 | I7: 24.17 | J7: Brasil | K7: XBSP | L7: BRL | M7: 1 | N7: BRL | O7: =F7+O6 -> 39.1 | P7: =F7*100/SUM($F$2:$F$21) -> 4.7142443
A8: ELET3 | B8: CENTRAIS ELETR BRAS-ELETROBRAS | C8: Energia Elétrica | D8: Renda VariÃ¡vel | E8: 1938106.2 | F8: 3.2 | G8: 1938106.2 | H8: 56786 | I8: 34.13 | J8: Brasil | K8: XBSP | L8: BRL | M8: 1 | N8: BRL | O8: =F8+O7 -> 42.3 | P8: =F8*100/SUM($F$2:$F$21) -> 4.6417174
A9: SBSP3 | B9: COMPANHIA DE SANEAMENTO BASICO DE | C9: Água e Saneamento | D9: Renda VariÃ¡vel | E9: 1735750.5 | F9: 2.86 | G9: 1735750.5 | H9: 19613 | I9: 88.5 | J9: Brasil | K9: XBSP | L9: BRL | M9: 1 | N9: BRL | O9: =F9+O8 -> 45.16 | P9: =F9*100/SUM($F$2:$F$21) -> 4.148535
A10: BBDC4 | B10: BANCO BRADESCO PREF SA | C10: Intermediários Financeiros | D10: Renda VariÃ¡vel | E10: 1703435.4 | F10: 2.81 | G10: 1703435.4 | H10: 147356 | I10: 11.56 | J10: Brasil | K10: XBSP | L10: BRL | M10: 1 | N10: BRL | O10: =F10+O9 -> 47.97 | P10: =F10*100/SUM($F$2:$F$21) -> 4.0760081
A11: B3SA3 | B11: B3 BRASIL BOLSA BALCAO SA | C11: Serviços Financeiros Diversos | D11: Renda VariÃ¡vel | E11: 1633872.7 | F11: 2.69 | G11: 1633872.7 | H11: 158321 | I11: 10.32 | J11: Brasil | K11: XBSP | L11: BRL | M11: 1 | N11: BRL | O11: =F11+O10 -> 50.66 | P11: =F11*100/SUM($F$2:$F$21) -> 3.9019437
A12: ABEV3 | B12: AMBEV SA | C12: Bebidas | D12: Renda VariÃ¡vel | E12: 1480496.2 | F12: 2.44 | G12: 1480496.2 | H12: 126107 | I12: 11.74 | J12: Brasil | K12: XBSP | L12: BRL | M12: 1 | N12: BRL | O12: =F12+O11 -> 53.1 | P12: =F12*100/SUM($F$2:$F$21) -> 3.5393095
A13: ITSA4 | B13: ITAUSA INVESTIMENTOS ITAU PREF SA | C13: Intermediários Financeiros | D13: Renda VariÃ¡vel | E13: 1464455.5 | F13: 2.42 | G13: 1464455.5 | H13: 165850 | I13: 8.83 | J13: Brasil | K13: XBSP | L13: BRL | M13: 1 | N13: BRL | O13: =F13+O12 -> 55.52 | P13: =F13*100/SUM($F$2:$F$21) -> 3.5102988
A14: JBSS3 | B14: JBS SA | C14: Alimentos Processados | D14: Renda VariÃ¡vel | E14: 1190240.7 | F14: 1.96 | G14: 1190240.7 | H14: 32789 | I14: 36.3 | J14: Brasil | K14: XBSP | L14: BRL | M14: 1 | N14: BRL | O14: =F14+O13 -> 57.48 | P14: =F14*100/SUM($F$2:$F$21) -> 2.8430519
... A21: RDOR3 | B21: REDE DOR SAO LUIZ SA | C21: Serv. Méd. Hospit. Análises e Diagnósticos | D21: Renda VariÃ¡vel | E21: 835377.46 | F21: 1.38 | G21: 835377.46 | H21: 32863 | I21: 25.42 | J21: Brasil | K21: XBSP | L21: BRL | M21: 1 | N21: BRL | O21: =F21+O20 -> 68.94 | P21: =F21*100/SUM($F$2:$F$21) -> 2.0017406

Sheet Ex_Carteira
A1: Ticker | B1: Name | C1: Sector | D1: Asset Class | E1: Market Value | F1: Weight (%) | G1: Notional Value | H1: Shares | I1: Price | J1: Location | K1: Exchange | L1: Currency | M1: FX Rate | N1: Market Currency | O1: Frequencia
A2: RADL3 | B2: RAIA DROGASIL | C2: Bens de primeira necessidade | D2: Renda VariÃ¡vel | E2: 807884 | F2: 1.33 | G2: 807884 | H2: 36722 | I2: 22 | J2: Brasil | K2: XBSP | L2: BRL | M2: 1 | N2: BRL
A3: BBSE3 | B3: BB SEGURIDADE SA | C3: Produtos financeiros | D3: Renda VariÃ¡vel | E3: 661659.84 | F3: 1.09 | G3: 661659.84 | H3: 18288 | I3: 36.18 | J3: Brasil | K3: XBSP | L3: BRL | M3: 1 | N3: BRL
A4: GGBR4 | B4: GERDAU PREF SA | C4: Materiais | D4: Renda VariÃ¡vel | E4: 646836.12 | F4: 1.07 | G4: 646836.12 | H4: 35658 | I4: 18.14 | J4: Brasil | K4: XBSP | L4: BRL | M4: 1 | N4: BRL
A5: RAIL3 | B5: RUMO SA | C5: Bens Industriais | D5: Renda VariÃ¡vel | E5: 622473.28 | F5: 1.03 | G5: 622473.28 | H5: 34892 | I5: 17.84 | J5: Brasil | K5: XBSP | L5: BRL | M5: 1 | N5: BRL
A6: BRFS3 | B6: BRF BRASIL FOODS SA | C6: Bens de primeira necessidade | D6: Renda VariÃ¡vel | E6: 592713.92 | F6: 0.98 | G6: 592713.92 | H6: 23372 | I6: 25.36 | J6: Brasil | K6: XBSP | L6: BRL | M6: 1 | N6: BRL
A7: CMIG4 | B7: CIA ENERGETICA DE MINAS GERAIS PRE | C7: ServiÃ§os pÃºblicos | D7: Renda VariÃ¡vel | E7: 592529.63 | F7: 0.98 | G7: 592529.63 | H7: 53333 | I7: 11.11 | J7: Brasil | K7: XBSP | L7: BRL | M7: 1 | N7: BRL
A8: VIVT3 | B8: TELEFONICA BRASIL SA | C8: ComunicaÃ§Ã£o | D8: Renda VariÃ¡vel | E8: 546554.22 | F8: 0.9 | G8: 546554.22 | H8: 11686 | I8: 46.77 | J8: Brasil | K8: XBSP | L8: BRL | M8: 1 | N8: BRL
A9: ENEV3 | B9: ENEVA SA | C9: ServiÃ§os pÃºblicos | D9: Renda VariÃ¡vel | E9: 546412.23 | F9: 0.9 | G9: 546412.23 | H9: 51891 | I9: 10.53 | J9: Brasil | K9: XBSP | L9: BRL | M9: 1 | N9: BRL
A10: VBBR3 | B10: VIBRA ENERGIA SA | C10: Consumo discricionÃ¡rio | D10: Renda VariÃ¡vel | E10: 523889.44 | F10: 0.86 | G10: 523889.44 | H10: 29366 | I10: 17.84 | J10: Brasil | K10: XBSP | L10: BRL | M10: 1 | N10: BRL
A11: KLBN11 | B11: KLABIN UNITS SA | C11: Materiais | D11: Renda VariÃ¡vel | E11: 509796.8 | F11: 0.84 | G11: 509796.8 | H11: 21974 | I11: 23.2 | J11: Brasil | K11: XBSP | L11: BRL | M11: 1 | N11: BRL
A12: UGPA3 | B12: ULTRAPAR PARTICIPOES SA | C12: Energia | D12: Renda VariÃ¡vel | E12: 496742.28 | F12: 0.82 | G12: 496742.28 | H12: 31281 | I12: 15.88 | J12: Brasil | K12: XBSP | L12: BRL | M12: 1 | N12: BRL
A13: BBDC3 | B13: BANCO BRADESCO SA | C13: Produtos financeiros | D13: Renda VariÃ¡vel | E13: 453210.8 | F13: 0.75 | G13: 453210.8 | H13: 42595 | I13: 10.64 | J13: Brasil | K13: XBSP | L13: BRL | M13: 1 | N13: BRL
... A84: KLBN4 | B84: KLABIN SA PREF | C84: Materiais | D84: Renda VariÃ¡vel | E84: 4.59 | F84: 0 | G84: 4.59 | H84: 1 | I84: 4.59 | J84: Brasil | K84: XBSP | L84: BRL | M84: 1 | N84: BRL

Sheet Cotacoes
A1: Data | B1: BRAX11 | C1: VALE3 | D1: PETR4 | E1: ITUB4 | F1: PETR3 | G1: WEGE3 | H1: BBAS3 | I1: ELET3 | J1: SBSP3 | K1: BBDC4 | L1: B3SA3 | M1: ABEV3 | N1: ITSA4 | O1: JBSS3 | P1: EMBR3 | Q1: SUZB3 | R1: BPAC11 | S1: EQTL3 | T1: PRIO3 | U1: RENT3 | V1: RDOR3
A2: 44564 | B2: 87.36 | C2: 57.05 | D2: 10.7 | E2: 15.97 | F2: 12.62 | G2: 29.98 | H2: 10.61 | I2: 28.88 | J2: 39.95 | K2: 14.09 | L2: 9.63 | M2: 12.99 | N2: 5.75 | O2: 36.35 | P2: 25.21 | Q2: 53.61 | R2: 18.48 | S2: 22.07 | T2: 20.26 | U2: 45.65 | V2: 41.52
A3: 44565 | B3: 86.7 | C3: 56.37 | D3: 10.74 | E3: 16.42 | F3: 12.78 | G3: 29.83 | H3: 10.62 | I3: 28.27 | J3: 38.85 | K3: 14.18 | L3: 9.83 | M3: 12.97 | N3: 5.79 | O3: 36.24 | P3: 25.19 | Q3: 54.78 | R3: 18.14 | S3: 21.87 | T3: 20.69 | U3: 45.91 | V3: 40.5
A4: 44566 | B4: 85.06 | C4: 56.91 | D4: 10.32 | E4: 16.11 | F4: 12.25 | G4: 28.26 | H4: 10.44 | I4: 28.15 | J4: 37.18 | K4: 14.08 | L4: 9.63 | M4: 12.72 | N4: 5.73 | O4: 36.16 | P4: 23.7 | Q4: 54.16 | R4: 17.2 | S4: 21.58 | T4: 18.46 | U4: 44.58 | V4: 37.76
A5: 44567 | B5: 85.2 | C5: 58.06 | D5: 10.31 | E5: 16.44 | F5: 12.24 | G5: 28.25 | H5: 10.52 | I5: 28.11 | J5: 36.21 | K5: 14.28 | L5: 9.86 | M5: 12.51 | N5: 5.78 | O5: 36.18 | P5: 23.85 | Q5: 53.73 | R5: 17.08 | S5: 21.4 | T5: 18.93 | U5: 44.76 | V5: 38.17
A6: 44568 | B6: 86.25 | C6: 61.43 | D6: 10.36 | E6: 16.8 | F6: 12.34 | G6: 27.54 | H6: 10.54 | I6: 26.88 | J6: 35.46 | K6: 14.49 | L6: 10.09 | M6: 12.31 | N6: 5.85 | O6: 35.24 | P6: 24.05 | Q6: 53.37 | R6: 17.17 | S6: 21.35 | T6: 19.79 | U6: 44.38 | V6: 38.86
A7: 44571 | B7: 86 | C7: 60.7 | D7: 10.3 | E7: 16.96 | F7: 12.3 | G7: 26.74 | H7: 10.59 | I7: 26.1 | J7: 34.78 | K7: 14.54 | L7: 10.04 | M7: 12.41 | N7: 5.85 | O7: 35.9 | P7: 23.72 | Q7: 53.24 | R7: 17.25 | S7: 21.72 | T7: 20.11 | U7: 43.51 | V7: 37.26
A8: 44572 | B8: 87.6 | C8: 61.86 | D8: 10.6 | E8: 17.34 | F8: 12.8 | G8: 27.19 | H8: 10.63 | I8: 26.41 | J8: 34.81 | K8: 14.56 | L8: 10.07 | M8: 12.44 | N8: 5.94 | O8: 35.71 | P8: 23.46 | Q8: 53.56 | R8: 18.01 | S8: 22.21 | T8: 21.17 | U8: 44.14 | V8: 38.53
A9: 44573 | B9: 89 | C9: 62.53 | D9: 10.93 | E9: 17.26 | F9: 13.23 | G9: 28.3 | H9: 10.74 | I9: 27.8 | J9: 35.28 | K9: 14.45 | L9: 10.43 | M9: 12.61 | N9: 5.92 | O9: 36.43 | P9: 23.09 | Q9: 55.44 | R9: 18.25 | S9: 22.75 | T9: 21.33 | U9: 44.51 | V9: 38.9
A10: 44574 | B10: 88.7 | C10: 61.58 | D10: 11.15 | E10: 17.58 | F10: 13.55 | G10: 27.11 | H10: 10.91 | I10: 27.81 | J10: 35.25 | K10: 14.71 | L10: 10.41 | M10: 12.7 | N10: 6.09 | O10: 37.06 | P10: 22.12 | Q10: 56.26 | R10: 17.75 | S10: 22.59 | T10: 21.98 | U10: 44.36 | V10: 39.09
A11: 44575 | B11: 90 | C11: 61.94 | D11: 11.56 | E11: 17.45 | F11: 13.83 | G11: 28.75 | H11: 11.19 | I11: 27.98 | J11: 35.11 | K11: 14.95 | L11: 10.97 | M11: 12.79 | N11: 6.16 | O11: 37.39 | P11: 21.99 | Q11: 56.47 | R11: 18.28 | S11: 22.62 | T11: 22.86 | U11: 45.99 | V11: 38.71
A12: 44578 | B12: 89.2 | C12: 61.62 | D12: 11.58 | E12: 17.45 | F12: 13.79 | G12: 28.42 | H12: 11.21 | I12: 28.05 | J12: 35.41 | K12: 15.03 | L12: 11.1 | M12: 12.54 | N12: 6.15 | O12: 36.98 | P12: 21.53 | Q12: 55.81 | R12: 18.19 | S12: 22.29 | T12: 22.78 | U12: 45.28 | V12: 37.38
A13: 44579 | B13: 89.57 | C13: 63.12 | D13: 11.63 | E13: 17.55 | F13: 13.84 | G13: 28.6 | H13: 11.31 | I13: 28.06 | J13: 34.86 | K13: 15.31 | L13: 11.06 | M13: 12.35 | N13: 6.19 | O13: 36.6 | P13: 21.15 | Q13: 56.55 | R13: 17.4 | S13: 21.84 | T13: 23.88 | U13: 44.59 | V13: 36.73
... A750: 45656 | B750: 101.85 | C750: 50.99 | D750: 34.1 | E750: 26.17 | F750: 37.28 | G750: 51.88 | H750: 23.31 | I750: 32.11 | J750: 88.5 | K750: 10.7 | L750: 10.12 | M750: 11.41 | N750: 8.08 | O750: 36.3 | P750: 56.13 | Q750: 61.78 | R750: 26.73 | S750: 27.4 | T750: 40.15 | U750: 31.16 | V750: 25.05

Sheet Retorno
A1: Data | B1: BRAX11 | C1: VALE3 | D1: PETR4 | E1: ITUB4 | F1: PETR3 | G1: WEGE3 | H1: BBAS3 | I1: ELET3 | J1: SBSP3 | K1: BBDC4 | L1: B3SA3 | M1: ABEV3 | N1: ITSA4 | O1: JBSS3 | P1: EMBR3 | Q1: SUZB3 | R1: BPAC11 | S1: EQTL3 | T1: PRIO3 | U1: RENT3 | V1: RDOR3
A2: 44564
A3: 44565 | B3: =(Cotacoes!B3-Cotacoes!B2)/Cotacoes!B2 -> -0.0075549451 | C3: =(Cotacoes!C3-Cotacoes!C2)/Cotacoes!C2 -> -0.011919369 | D3: =(Cotacoes!D3-Cotacoes!D2)/Cotacoes!D2 -> 0.0037383178 | E3: =(Cotacoes!E3-Cotacoes!E2)/Cotacoes!E2 -> 0.028177833 | F3: =(Cotacoes!F3-Cotacoes!F2)/Cotacoes!F2 -> 0.012678288 | G3: =(Cotacoes!G3-Cotacoes!G2)/Cotacoes!G2 -> -0.0050033356 | H3: =(Cotacoes!H3-Cotacoes!H2)/Cotacoes!H2 -> 0.00094250707 | I3: =(Cotacoes!I3-Cotacoes!I2)/Cotacoes!I2 -> -0.021121884 | ... V3: =(Cotacoes!V3-Cotacoes!V2)/Cotacoes!V2 -> -0.024566474
A4: 44566 | B4: =(Cotacoes!B4-Cotacoes!B3)/Cotacoes!B3 -> -0.018915802 | C4: =(Cotacoes!C4-Cotacoes!C3)/Cotacoes!C3 -> 0.0095795636 | D4: =(Cotacoes!D4-Cotacoes!D3)/Cotacoes!D3 -> -0.039106145 | E4: =(Cotacoes!E4-Cotacoes!E3)/Cotacoes!E3 -> -0.018879415 | F4: =(Cotacoes!F4-Cotacoes!F3)/Cotacoes!F3 -> -0.041471049 | G4: =(Cotacoes!G4-Cotacoes!G3)/Cotacoes!G3 -> -0.052631579 | H4: =(Cotacoes!H4-Cotacoes!H3)/Cotacoes!H3 -> -0.016949153 | I4: =(Cotacoes!I4-Cotacoes!I3)/Cotacoes!I3 -> -0.0042447825 | ... V4: =(Cotacoes!V4-Cotacoes!V3)/Cotacoes!V3 -> -0.067654321
A5: 44567 | B5: =(Cotacoes!B5-Cotacoes!B4)/Cotacoes!B4 -> 0.001645897 | C5: =(Cotacoes!C5-Cotacoes!C4)/Cotacoes!C4 -> 0.020207345 | D5: =(Cotacoes!D5-Cotacoes!D4)/Cotacoes!D4 -> -0.00096899225 | E5: =(Cotacoes!E5-Cotacoes!E4)/Cotacoes!E4 -> 0.020484171 | F5: =(Cotacoes!F5-Cotacoes!F4)/Cotacoes!F4 -> -0.00081632653 | G5: =(Cotacoes!G5-Cotacoes!G4)/Cotacoes!G4 -> -0.00035385704 | H5: =(Cotacoes!H5-Cotacoes!H4)/Cotacoes!H4 -> 0.0076628352 | I5: =(Cotacoes!I5-Cotacoes!I4)/Cotacoes!I4 -> -0.0014209591 | ... V5: =(Cotacoes!V5-Cotacoes!V4)/Cotacoes!V4 -> 0.010858051
A6: 44568 | B6: =(Cotacoes!B6-Cotacoes!B5)/Cotacoes!B5 -> 0.012323944 | C6: =(Cotacoes!C6-Cotacoes!C5)/Cotacoes!C5 -> 0.058043403 | D6: =(Cotacoes!D6-Cotacoes!D5)/Cotacoes!D5 -> 0.0048496605 | E6: =(Cotacoes!E6-Cotacoes!E5)/Cotacoes!E5 -> 0.02189781 | F6: =(Cotacoes!F6-Cotacoes!F5)/Cotacoes!F5 -> 0.0081699346 | G6: =(Cotacoes!G6-Cotacoes!G5)/Cotacoes!G5 -> -0.025132743 | H6: =(Cotacoes!H6-Cotacoes!H5)/Cotacoes!H5 -> 0.0019011407 | I6: =(Cotacoes!I6-Cotacoes!I5)/Cotacoes!I5 -> -0.04375667 | ... V6: =(Cotacoes!V6-Cotacoes!V5)/Cotacoes!V5 -> 0.018077024
A7: 44571 | B7: =(Cotacoes!B7-Cotacoes!B6)/Cotacoes!B6 -> -0.0028985507 | C7: =(Cotacoes!C7-Cotacoes!C6)/Cotacoes!C6 -> -0.011883445 | D7: =(Cotacoes!D7-Cotacoes!D6)/Cotacoes!D6 -> -0.0057915058 | E7: =(Cotacoes!E7-Cotacoes!E6)/Cotacoes!E6 -> 0.0095238095 | F7: =(Cotacoes!F7-Cotacoes!F6)/Cotacoes!F6 -> -0.0032414911 | G7: =(Cotacoes!G7-Cotacoes!G6)/Cotacoes!G6 -> -0.029048656 | H7: =(Cotacoes!H7-Cotacoes!H6)/Cotacoes!H6 -> 0.004743833 | I7: =(Cotacoes!I7-Cotacoes!I6)/Cotacoes!I6 -> -0.029017857 | ... V7: =(Cotacoes!V7-Cotacoes!V6)/Cotacoes!V6 -> -0.041173443
A8: 44572 | B8: =(Cotacoes!B8-Cotacoes!B7)/Cotacoes!B7 -> 0.018604651 | C8: =(Cotacoes!C8-Cotacoes!C7)/Cotacoes!C7 -> 0.019110379 | D8: =(Cotacoes!D8-Cotacoes!D7)/Cotacoes!D7 -> 0.029126214 | E8: =(Cotacoes!E8-Cotacoes!E7)/Cotacoes!E7 -> 0.02240566 | F8: =(Cotacoes!F8-Cotacoes!F7)/Cotacoes!F7 -> 0.040650407 | G8: =(Cotacoes!G8-Cotacoes!G7)/Cotacoes!G7 -> 0.016828721 | H8: =(Cotacoes!H8-Cotacoes!H7)/Cotacoes!H7 -> 0.0037771483 | I8: =(Cotacoes!I8-Cotacoes!I7)/Cotacoes!I7 -> 0.011877395 | ... V8: =(Cotacoes!V8-Cotacoes!V7)/Cotacoes!V7 -> 0.034084809
A9: 44573 | B9: =(Cotacoes!B9-Cotacoes!B8)/Cotacoes!B8 -> 0.015981735 | C9: =(Cotacoes!C9-Cotacoes!C8)/Cotacoes!C8 -> 0.010830909 | D9: =(Cotacoes!D9-Cotacoes!D8)/Cotacoes!D8 -> 0.031132075 | E9: =(Cotacoes!E9-Cotacoes!E8)/Cotacoes!E8 -> -0.0046136101 | F9: =(Cotacoes!F9-Cotacoes!F8)/Cotacoes!F8 -> 0.03359375 | G9: =(Cotacoes!G9-Cotacoes!G8)/Cotacoes!G8 -> 0.040823832 | H9: =(Cotacoes!H9-Cotacoes!H8)/Cotacoes!H8 -> 0.010348071 | I9: =(Cotacoes!I9-Cotacoes!I8)/Cotacoes!I8 -> 0.052631579 | ... V9: =(Cotacoes!V9-Cotacoes!V8)/Cotacoes!V8 -> 0.0096029068
A10: 44574 | B10: =(Cotacoes!B10-Cotacoes!B9)/Cotacoes!B9 -> -0.0033707865 | C10: =(Cotacoes!C10-Cotacoes!C9)/Cotacoes!C9 -> -0.015192708 | D10: =(Cotacoes!D10-Cotacoes!D9)/Cotacoes!D9 -> 0.020128088 | E10: =(Cotacoes!E10-Cotacoes!E9)/Cotacoes!E9 -> 0.018539977 | F10: =(Cotacoes!F10-Cotacoes!F9)/Cotacoes!F9 -> 0.024187453 | G10: =(Cotacoes!G10-Cotacoes!G9)/Cotacoes!G9 -> -0.04204947 | H10: =(Cotacoes!H10-Cotacoes!H9)/Cotacoes!H9 -> 0.015828678 | I10: =(Cotacoes!I10-Cotacoes!I9)/Cotacoes!I9 -> 0.00035971223 | ... V10: =(Cotacoes!V10-Cotacoes!V9)/Cotacoes!V9 -> 0.0048843188
A11: 44575 | B11: =(Cotacoes!B11-Cotacoes!B10)/Cotacoes!B10 -> 0.014656144 | C11: =(Cotacoes!C11-Cotacoes!C10)/Cotacoes!C10 -> 0.0058460539 | D11: =(Cotacoes!D11-Cotacoes!D10)/Cotacoes!D10 -> 0.0367713 | E11: =(Cotacoes!E11-Cotacoes!E10)/Cotacoes!E10 -> -0.0073947668 | F11: =(Cotacoes!F11-Cotacoes!F10)/Cotacoes!F10 -> 0.020664207 | G11: =(Cotacoes!G11-Cotacoes!G10)/Cotacoes!G10 -> 0.060494283 | H11: =(Cotacoes!H11-Cotacoes!H10)/Cotacoes!H10 -> 0.025664528 | I11: =(Cotacoes!I11-Cotacoes!I10)/Cotacoes!I10 -> 0.006112909 | ... V11: =(Cotacoes!V11-Cotacoes!V10)/Cotacoes!V10 -> -0.0097211563
A12: 44578 | B12: =(Cotacoes!B12-Cotacoes!B11)/Cotacoes!B11 -> -0.0088888889 | C12: =(Cotacoes!C12-Cotacoes!C11)/Cotacoes!C11 -> -0.00516629 | D12: =(Cotacoes!D12-Cotacoes!D11)/Cotacoes!D11 -> 0.0017301038 | E12: =(Cotacoes!E12-Cotacoes!E11)/Cotacoes!E11 -> 0 | F12: =(Cotacoes!F12-Cotacoes!F11)/Cotacoes!F11 -> -0.0028922632 | G12: =(Cotacoes!G12-Cotacoes!G11)/Cotacoes!G11 -> -0.011478261 | H12: =(Cotacoes!H12-Cotacoes!H11)/Cotacoes!H11 -> 0.0017873101 | I12: =(Cotacoes!I12-Cotacoes!I11)/Cotacoes!I11 -> 0.002501787 | ... V12: =(Cotacoes!V12-Cotacoes!V11)/Cotacoes!V11 -> -0.034358047
A13: 44579 | B13: =(Cotacoes!B13-Cotacoes!B12)/Cotacoes!B12 -> 0.0041479821 | C13: =(Cotacoes!C13-Cotacoes!C12)/Cotacoes!C12 -> 0.024342746 | D13: =(Cotacoes!D13-Cotacoes!D12)/Cotacoes!D12 -> 0.0043177893 | E13: =(Cotacoes!E13-Cotacoes!E12)/Cotacoes!E12 -> 0.005730659 | F13: =(Cotacoes!F13-Cotacoes!F12)/Cotacoes!F12 -> 0.0036258158 | G13: =(Cotacoes!G13-Cotacoes!G12)/Cotacoes!G12 -> 0.0063335679 | H13: =(Cotacoes!H13-Cotacoes!H12)/Cotacoes!H12 -> 0.0089206066 | I13: =(Cotacoes!I13-Cotacoes!I12)/Cotacoes!I12 -> 0.00035650624 | ... V13: =(Cotacoes!V13-Cotacoes!V12)/Cotacoes!V12 -> -0.017388978
A14: 44580 | B14: =(Cotacoes!B14-Cotacoes!B13)/Cotacoes!B13 -> 0.0163001 | C14: =(Cotacoes!C14-Cotacoes!C13)/Cotacoes!C13 -> 0.022021546 | D14: =(Cotacoes!D14-Cotacoes!D13)/Cotacoes!D13 -> -0.0042992261 | E14: =(Cotacoes!E14-Cotacoes!E13)/Cotacoes!E13 -> -0.0068376068 | F14: =(Cotacoes!F14-Cotacoes!F13)/Cotacoes!F13 -> -0.0093930636 | G14: =(Cotacoes!G14-Cotacoes!G13)/Cotacoes!G13 -> -0.0013986014 | H14: =(Cotacoes!H14-Cotacoes!H13)/Cotacoes!H13 -> 0.008841733 | I14: =(Cotacoes!I14-Cotacoes!I13)/Cotacoes!I13 -> 0.042409123 | ... V14: =(Cotacoes!V14-Cotacoes!V13)/Cotacoes!V13 -> 0.03185407
... A750: 45656 | B750: =(Cotacoes!B750-Cotacoes!B749)/Cotacoes!B749 -> 0 | C750: =(Cotacoes!C750-Cotacoes!C749)/Cotacoes!C749 -> -0.0035176861 | D750: =(Cotacoes!D750-Cotacoes!D749)/Cotacoes!D749 -> 0.014880952 | E750: =(Cotacoes!E750-Cotacoes!E749)/Cotacoes!E749 -> -0.0015261351 | F750: =(Cotacoes!F750-Cotacoes!F749)/Cotacoes!F749 -> 0.014697877 | G750: =(Cotacoes!G750-Cotacoes!G749)/Cotacoes!G749 -> -0.017051914 | H750: =(Cotacoes!H750-Cotacoes!H749)/Cotacoes!H749 -> 0.0025806452 | I750: =(Cotacoes!I750-Cotacoes!I749)/Cotacoes!I749 -> 0 | ... V750: =(Cotacoes!V750-Cotacoes!V749)/Cotacoes!V749 -> 0.0056202328
